COPYING
MANIFEST.in
README
health_report.xml
health_view.xml
setup.py
./__init__.py
./health.py
./health_report.xml
./health_view.xml
./tryton.cfg
./data/dose_units.xml
./data/drug_administration_routes.xml
./data/ethnic_groups.xml
./data/health_product.xml
./data/health_sequences.xml
./data/health_specialties.xml
./data/medicament_form.xml
./data/medication_frequencies.xml
./data/occupations.xml
./data/pathology_groups.xml
./doc/index.rst
./icons/appointment.svg
./icons/cancel.svg
./icons/demography.svg
./icons/doctor.svg
./icons/face-sick.svg
./icons/gnuhealth_icon.svg
./icons/hand-scalpel.svg
./icons/health-center.svg
./icons/immunizations.svg
./icons/medicament.svg
./icons/ok.svg
./icons/patient.svg
./icons/prescription.svg
./icons/report.svg
./icons/stop.svg
./icons/tryton-list.svg
./icons/tryton-open.svg
./icons/tryton-preferences.svg
./icons/warning.svg
./locale/ar.po
./locale/de.po
./locale/el.po
./locale/es.po
./locale/fr.po
./locale/it_IT.po
./locale/ja_JP.po
./locale/lo.po
./locale/pt_BR.po
./locale/zh_CN.po
./report/__init__.py
./report/appointment_receipt.odt
./report/default_gnuhealth_report_template.odt
./report/health_report.py
./report/immunization_status_report.odt
./report/immunization_status_report.py
./report/patient_card.odt
./report/patient_conditions_history.odt
./report/patient_evaluation.odt
./report/patient_medication_history.odt
./report/patient_vaccination_history.odt
./report/prescription_orders.odt
./security/access_rights.xml
./tests/__init__.py
./tests/test_health.py
./view/address_tree.xml
./view/appointments_report_open_start_form.xml
./view/appointments_report_tree.xml
./view/check_immunization_status.xml
./view/contact_mechanism_tree.xml
./view/gnuhealth_alternative_identification_form.xml
./view/gnuhealth_alternative_identification_tree.xml
./view/gnuhealth_appointment_form.xml
./view/gnuhealth_appointment_tree.xml
./view/gnuhealth_birth_certificate_form.xml
./view/gnuhealth_birth_certificate_tree.xml
trytond_health.egg-info/PKG-INFO
trytond_health.egg-info/SOURCES.txt
trytond_health.egg-info/dependency_links.txt
trytond_health.egg-info/entry_points.txt
trytond_health.egg-info/not-zip-safe
trytond_health.egg-info/requires.txt
trytond_health.egg-info/top_level.txt
